src/__init__.py
src/cache/__init__.py
src/cache/base_cache.py
src/cache/core_cache.py
src/cache/mem_cache.py
src/cache/redis_cache.py
src/config/cache_config.py
src/py.typed
cachemaster-0.1.0.dist-info/LICENSE
cachemaster-0.1.0.dist-info/METADATA
cachemaster-0.1.0.dist-info/WHEEL
cachemaster-0.1.0.dist-info/RECORD
