Metadata-Version: 2.3
Name: CacheMaster
Version: 0.1.0
Summary: A flexible caching system with in-memory and Redis support
License: MIT
Author: Janardhan Singh
Author-email: janardhansingh1998@gmail.com
Requires-Python: >=3.8,<4.0
Classifier: Programming Language :: Python :: 3
Classifier: License :: OSI Approved :: MIT License
Classifier: Operating System :: OS Independent
Requires-Dist: redis (>=4.0.0)
Requires-Dist: ruff (>=0.11.6,<0.12.0)
Project-URL: Documentation, https://github.com/JanardhanSingh98/CacheMaster
Project-URL: Homepage, https://github.com/JanardhanSingh98/CacheMaster
Project-URL: Issues, https://github.com/JanardhanSingh98/CacheMaster/issues
Project-URL: Repository, https://github.com/JanardhanSingh98/CacheMaster
